client.py
models/__init__.py
routers/__init__.py
routers/api_keys.py
services/__init__.py
services/api_key_service.py
services/db_transaction.py
services/sas_function_app.py
services/sas_token_generator.py
services/table_storage.py
services/token_service.py
tests/__init__.py
tests/direct_test_sas.py
tests/run_sas_test.py
tests/sas_test.py
tests/test_api_integration.py
tests/test_api_keys.py
tests/test_sas_integration.py
tests/test_sas_token_generator.py
tests/test_table_storage.py
tests/test_table_storage_client.py
tests/test_token_service_integration.py
tests/test_token_service_sas.py
auth_api_client-1.0.1.dist-info/METADATA
auth_api_client-1.0.1.dist-info/WHEEL
auth_api_client-1.0.1.dist-info/top_level.txt
auth_api_client-1.0.1.dist-info/RECORD
