Metadata-Version: 2.4
Name: auth-api-client
Version: 1.0.1
Summary: A robust client for interacting with the Auth API service
Home-page: https://github.com/perceptivefocus/auth
Author: Perceptive Focus
Author-email: info@perceptivefocus.com
Project-URL: Bug Tracker, https://github.com/perceptivefocus/auth/issues
Project-URL: Documentation, https://github.com/perceptivefocus/auth/blob/main/api_keys/README.md
Project-URL: Source Code, https://github.com/perceptivefocus/auth
Keywords: api,authentication,client,api-key
Classifier: Programming Language :: Python :: 3
Classifier: Programming Language :: Python :: 3.8
Classifier: Programming Language :: Python :: 3.9
Classifier: Programming Language :: Python :: 3.10
Classifier: Programming Language :: Python :: 3.11
Classifier: License :: OSI Approved :: MIT License
Classifier: Operating System :: OS Independent
Classifier: Development Status :: 5 - Production/Stable
Requires-Python: >=3.8
Requires-Dist: requests>=2.25.0
Requires-Dist: pydantic>=2.0.0
Requires-Dist: python-dateutil>=2.8.1
Requires-Dist: urllib3>=1.26.0
Requires-Dist: azure-storage-table>=2.0.0
Requires-Dist: azure-storage-blob>=12.0.0
Requires-Dist: azure-identity>=1.5.0
Dynamic: author
Dynamic: author-email
Dynamic: classifier
Dynamic: description
Dynamic: description-content-type
Dynamic: home-page
Dynamic: keywords
Dynamic: project-url
Dynamic: requires-dist
Dynamic: requires-python
Dynamic: summary
